{
    "code": 0,
    "data":[
    {
    "searchModels":[
    {
    "maxGuidePrice":85.63,
    "minGuidePrice":34.3,
    "modelID":"18",
    "modelName":"奥迪A6L"
    },
    {
    "maxGuidePrice":91,
    "minGuidePrice":91,
    "modelID":"2733",
    "modelName":"奥迪RS4"
    },
    {
    "maxGuidePrice":0,
    "minGuidePrice":0,
    "modelID":"2760",
    "modelName":"奥迪RSQ3"
    },
    {
    "maxGuidePrice":0,
    "minGuidePrice":0,
    "modelID":"3334",
    "modelName":"奥迪Q9"
    },
    {
    "maxGuidePrice":78,
    "minGuidePrice":39.58,
    "modelID":"471",
    "modelName":"奥迪A4(进口)"
    },
    {
    "maxGuidePrice":0,
    "minGuidePrice":0,
    "modelID":"3305",
    "modelName":"奥迪Q4(进口)"
    },
    {
    "maxGuidePrice":0,
    "minGuidePrice":0,
    "modelID":"3910",
    "modelName":"奥迪80"
    },
    {
    "maxGuidePrice":45.48,
    "minGuidePrice":45.48,
    "modelID":"4526",
    "modelName":"奥迪A6L新能源"
    },
    {
    "maxGuidePrice":0,
    "minGuidePrice":0,
    "modelID":"787",
    "modelName":"奥迪Cross"
    },
    {
    "maxGuidePrice":67.8,
    "minGuidePrice":57.7,
    "modelID":"593",
    "modelName":"奥迪Q5(进口)"
    },
    {
    "maxGuidePrice":36.98,
    "minGuidePrice":25.5,
    "modelID":"370",
    "modelName":"奥迪A3(进口)"
    },
    {
    "maxGuidePrice":0,
    "minGuidePrice":0,
    "modelID":"3304",
    "modelName":"奥迪Q4"
    },
    {
    "maxGuidePrice":139.1,
    "minGuidePrice":139.1,
    "modelID":"2737",
    "modelName":"奥迪RS6"
    },
    {
    "maxGuidePrice":57.81,
    "minGuidePrice":27.28,
    "modelID":"692",
    "modelName":"奥迪A4L"
    },
    {
    "maxGuidePrice":0,
    "minGuidePrice":0,
    "modelID":"4907",
    "modelName":"奥迪SQ2"
    },
    {
    "maxGuidePrice":198.8,
    "minGuidePrice":165,
    "modelID":"2739",
    "modelName":"奥迪S8"
    },
    {
    "maxGuidePrice":291.9,
    "minGuidePrice":85.8,
    "modelID":"146",
    "modelName":"奥迪A8"
    },
    {
    "maxGuidePrice":42.88,
    "minGuidePrice":23.42,
    "modelID":"2951",
    "modelName":"奥迪Q3"
    },
    {
    "maxGuidePrice":0,
    "minGuidePrice":0,
    "modelID":"3325",
    "modelName":"奥迪A0"
    },
    {
    "maxGuidePrice":39.98,
    "minGuidePrice":37.15,
    "modelID":"2730",
    "modelName":"长安欧尚"
    },
    {
    "maxGuidePrice":0,
    "minGuidePrice":0,
    "modelID":"3680",
    "modelName":"别克"
    },
    {
    "maxGuidePrice":0,
    "minGuidePrice":0,
    "modelID":"4998",
    "modelName":"布加迪"
    },
    {
    "maxGuidePrice":0,
    "minGuidePrice":0,
    "modelID":"3276",
    "modelName":"宾利"
    },
    {
    "maxGuidePrice":54.17,
    "minGuidePrice":30.8,
    "modelID":"509",
    "modelName":"成功汽车"
    },
    {
    "maxGuidePrice":31.18,
    "minGuidePrice":18.98,
    "modelID":"650",
    "modelName":"道奇"
    },
    {
    "maxGuidePrice":67.99,
    "minGuidePrice":36.98,
    "modelID":"538",
    "modelName":"东风风行"
    },
    {
    "maxGuidePrice":56.65,
    "minGuidePrice":27.49,
    "modelID":"19",
    "modelName":"东风风神"
    },
    {
    "maxGuidePrice":87.5,
    "minGuidePrice":80.88,
    "modelID":"4460",
    "modelName":"丰田"
    },
    {
    "maxGuidePrice":0,
    "minGuidePrice":0,
    "modelID":"3287",
    "modelName":"福田"
    },
    {
    "maxGuidePrice":178.8,
    "minGuidePrice":157.7,
    "modelID":"2994",
    "modelName":"福迪"
    },
    {
    "maxGuidePrice":27.9,
    "minGuidePrice":21.77,
    "modelID":"4871",
    "modelName":"广汽吉奥"
    },
    {
    "maxGuidePrice":57.17,
    "minGuidePrice":35.85,
    "modelID":"812",
    "modelName":"广汽新能源"
    },
    {
    "maxGuidePrice":135.8,
    "minGuidePrice":126.1,
    "modelID":"2738",
    "modelName":"广汽传祺"
    },
    {
    "maxGuidePrice":78.78,
    "minGuidePrice":78.78,
    "modelID":"2741",
    "modelName":"国金汽车"
    },
    {
    "maxGuidePrice":66.8,
    "minGuidePrice":66.8,
    "modelID":"2841",
    "modelName":"华凯"
    },
    {
    "maxGuidePrice":46.98,
    "minGuidePrice":46.98,
    "modelID":"2732",
    "modelName":"华骐"
    },
    {
    "maxGuidePrice":69,
    "minGuidePrice":46.45,
    "modelID":"148",
    "modelName":"黄海"
    },
    {
    "maxGuidePrice":110,
    "minGuidePrice":42.98,
    "modelID":"472",
    "modelName":"九龙"
    },
    {
    "maxGuidePrice":51.7,
    "minGuidePrice":39.28,
    "modelID":"4851",
    "modelName":"钧天"
    },
    {
    "maxGuidePrice":72.98,
    "minGuidePrice":61.18,
    "modelID":"2740",
    "modelName":"君马汽车"
    },
    {
    "maxGuidePrice":40.78,
    "minGuidePrice":39.98,
    "modelID":"4325",
    "modelName":"凯迪拉克"
    },
    {
    "maxGuidePrice":262.8,
    "minGuidePrice":182.3,
    "modelID":"511",
    "modelName":"凯翼"
    },
    {
    "maxGuidePrice":0,
    "minGuidePrice":0,
    "modelID":"4543",
    "modelName":"科尼赛克"
    },
    {
    "maxGuidePrice":0,
    "minGuidePrice":0,
    "modelID":"4895",
    "modelName":"陆风"
    },
    {
    "maxGuidePrice":0,
    "minGuidePrice":0,
    "modelID":"4544",
    "modelName":"罗夫哈特"
    },
    {
    "maxGuidePrice":0,
    "minGuidePrice":0,
    "modelID":"3822",
    "modelName":"玛莎拉蒂"
    },
    {
    "maxGuidePrice":257.8,
    "minGuidePrice":69.98,
    "modelID":"412",
    "modelName":"起亚"
    },
    {
    "maxGuidePrice":0,
    "minGuidePrice":0,
    "modelID":"4288",
    "modelName":"启辰"
    },
    {
    "maxGuidePrice":0,
    "minGuidePrice":0,
    "modelID":"3894",
    "modelName":"乔治·巴顿"
    },
    {
    "maxGuidePrice":0,
    "minGuidePrice":0,
    "modelID":"5046",
    "modelName":"全球鹰"
    },
    {
    "maxGuidePrice":0,
    "minGuidePrice":0,
    "modelID":"2415",
    "modelName":"如虎"
    },
    {
    "maxGuidePrice":0,
    "minGuidePrice":0,
    "modelID":"2832",
    "modelName":"瑞麒"
    },
    {
    "maxGuidePrice":47.9,
    "minGuidePrice":37.7,
    "modelID":"2264",
    "modelName":"瑞驰新能源"
    },
    {
    "maxGuidePrice":128.8,
    "minGuidePrice":109.8,
    "modelID":"2735",
    "modelName":"萨博"
    },
    {
    "maxGuidePrice":0,
    "minGuidePrice":0,
    "modelID":"2403",
    "modelName":"威兹曼"
    },
    {
    "maxGuidePrice":0,
    "minGuidePrice":0,
    "modelID":"3313",
    "modelName":"潍柴英致"
    },
    {
    "maxGuidePrice":0,
    "minGuidePrice":0,
    "modelID":"3909",
    "modelName":"一汽"
    },
    {
    "maxGuidePrice":105.8,
    "minGuidePrice":92.8,
    "modelID":"2736",
    "modelName":"五十铃"
    },
    {
    "maxGuidePrice":99.8,
    "minGuidePrice":63.58,
    "modelID":"2734",
    "modelName":"御捷"
    },
    {
    "maxGuidePrice":52.5,
    "minGuidePrice":52.5,
    "modelID":"2731",
    "modelName":"蔚来"
    },
    {
    "maxGuidePrice":0,
    "minGuidePrice":0,
    "modelID":"3479",
    "modelName":"云雀汽车"
    },
    {
    "maxGuidePrice":29.67,
    "minGuidePrice":18.49,
    "modelID":"3170",
    "modelName":"长城"
    },
    {
    "maxGuidePrice":95.8,
    "minGuidePrice":55.6,
    "modelID":"740",
    "modelName":"长安"
    }
    ]
    }
    ]
    }